exploratory_data_analysis/__init__.py
exploratory_data_analysis/data.py
exploratory_data_analysis/eda_functions.py
exploratory_data_analysis/tester.py
gatoeda65-0.0.4.dist-info/LICENSE
gatoeda65-0.0.4.dist-info/METADATA
gatoeda65-0.0.4.dist-info/WHEEL
gatoeda65-0.0.4.dist-info/top_level.txt
gatoeda65-0.0.4.dist-info/RECORD
